mcp_analyst/__init__.py
mcp_analyst/analyst.py
mcp_analyst-0.3.0.dist-info/METADATA
mcp_analyst-0.3.0.dist-info/WHEEL
mcp_analyst-0.3.0.dist-info/entry_points.txt
mcp_analyst-0.3.0.dist-info/top_level.txt
mcp_analyst-0.3.0.dist-info/RECORD
